src/params.sv
    parameter mem_file = "BENCH.x";
	parameter [31:0] mem_start = 32'h80020000;
	parameter mem_depth = 2**20; // 1 MB
	typedef enum { sz_byte, sz_word, sz_4word, sz_8word } mem_access_sizes;

src/regfile.sv
module regfile(
		input [4:0] wr_num, input [31:0] wr_data, input wr_en,
		input [4:0] rd0_num, output [31:0] rd0_data,
		input [4:0] rd1_num, output [31:0] rd1_data,
		input clk, reset);

	parameter [31:0] sp_init = 0;
	parameter [31:0] ra_init = 0;

    reg[31:0] data [1:31]; // general-purpose registers r1-r31 (r0===0)

	always @(posedge clk or posedge reset)
	if(reset) begin
		data[29] <= sp_init;
		data[31] <= ra_init;
	end
	else begin
        if(wr_en && wr_num!=0) data[wr_num] <= wr_data;
	end

   	assign rd0_data = (rd0_num!=0) ? data[rd0_num] : 32'h00000000;
   	assign rd1_data = (rd1_num!=0) ? data[rd1_num] : 32'h00000000;

endmodule

mips.sv
// this is a mips module that can only execute the addiu instruction
module mips(
	// port list
	input clk, reset,
	output [31:0] instr_addr,
	input [31:0] instr_in,
	output [31:0] data_addr,
	input [31:0] data_in,
	output logic [31:0] data_out,
	output data_rd_wr);

	// parameters overridden in testbench
	parameter [31:0] pc_init = 0;
	parameter [31:0] sp_init = 0;
	parameter [31:0] ra_init = 0;

	// IF signals
	logic [31:0] pc;
	assign instr_addr = pc;
	logic [31:0] ir;

	// ID signals
    logic [4:0] reg_rd_num0, reg_rd_num1, reg_rd_num2;
	logic [31:0] opcode, funct;
    wire [31:0] reg_rd_data0, reg_rd_data1;
	assign reg_rd_num0 = ir[25:21];
	assign reg_rd_num1 = ir[20:16];
	assign reg_rd_num2 = ir[15:11];
	assign opcode = ir[31:26];
	assign funct = ir[5:0];

	// EX signals
	logic [31:0] a, b, sign_ext_imm;
	logic [31:0] alu_out;
	logic [31:0] ex_op, ex_funct;
	logic [31:0] ex_pc;
	logic [4:0] ex_reg0, ex_reg1, ex_reg2;
	// Data forwarding
	logic [1:0] forward;
	logic fwd_reg;
	logic [31:0] forward_data;

	// ME signals
	logic st_en;
	assign data_out = b;
	assign data_rd_wr = ~st_en;
	assign data_addr = alu_out;
	logic [31:0] me_pc;
	logic [31:0] me_op, me_funct;
	logic [4:0] me_reg0, me_reg1, me_reg2;

	// WD signals
    logic [4:0] reg_wr_num;
    logic [31:0] reg_wr_data;
    logic reg_wr_en;
	logic [31:0] wb_op, wb_funct;
	logic [4:0] wb_reg1;
	logic [31:0] wb_pc;

	enum { init, idle, fetch, id, ex, me, wb } state;

	logic [31:0] jump, idle_ctrl;
	integer pfetch, pid, pex, pme, pwb;

	// register file
    regfile #(.sp_init(sp_init), .ra_init(ra_init)) regs(
		.wr_num(reg_wr_num), .wr_data(reg_wr_data), .wr_en(reg_wr_en),
        .rd0_num(reg_rd_num0), .rd0_data(reg_rd_data0),
		.rd1_num(reg_rd_num1), .rd1_data(reg_rd_data1),
        .clk(clk), .reset(reset));

	always @(posedge clk or posedge reset) begin
		if(reset) begin
			reg_wr_en <= 0;
			pc <= pc_init;
			state <= init;
		end
		else
			case(state)
				init: begin
					jump <= 1;

					pfetch = 0;
					pid = 0;
					pex = 0;
					pme = 0;
					pwb = 0;

					// this state is needed since we have to wait for
					// memory to produce the first instruction after reset
					forward <= 0;
					idle_ctrl <= 5;
					state <= idle;
				end
				idle: begin
					// TODO : IDLE to make startup
					idle_ctrl <= idle_ctrl - 1;
					case(idle_ctrl)
						0: begin
							state <= ex;
						end
						3: begin
							state <= fetch;
						end
						default:
							state <= idle;
					endcase
				end
				fetch: begin
					//$display("\nIF %h %h", alu_out, data_in);

					ir <= instr_in;
					pc <= pc + 4;
					pfetch += 1;

					case(jump)
						1: begin
							state <= id;
						end
						2: begin
							state <= idle;
						end
						4: begin
							state <= me;
						end
						13: begin
							state <= wb;
						end
						default:
							state <= wb;
					endcase
					
				end
				id: begin
					//$write(" [ID %h %h %h %h] ", a, b, data_in, alu_out);			
					// TODO : Return to fetch does not affect these regs.
					a <= reg_rd_data0;
					b <= reg_rd_data1;
					sign_ext_imm <= {{16{ir[15]}},ir[15:0]};
					
					//$display("calc imm: %h | ex alu %h", sign_ext_imm, alu_out);

					ex_op <= opcode;
					ex_funct <= funct;
					ex_reg0 <= reg_rd_num0;
					ex_reg1 <= reg_rd_num1;
					ex_reg2 <= reg_rd_num2;
					ex_pc <= pc;

					jump <= jump + 1;	
					state <= fetch;
					pid += 1;
				end
				ex: begin
					//$write(" [EX %h %h %h %h] ", a, b, data_in, alu_out);		
					//$display("\nEX %h %h", alu_out, data_in);

					if (ex_op == 'h0) // add*
					begin
						if (forward == 1)
						begin
							if (fwd_reg == 0)
							begin
								alu_out <= forward_data + b;
								forward_data <= forward_data + b;
							end
							else
							begin
								alu_out <= a + b;
								forward_data <= a + b;
							end
						end
						else
						begin
							alu_out <= a + b;
							forward_data <= a + b;
						end
					end
					else
					begin
						if (forward == 1 && fwd_reg == 0)
						begin
							alu_out <= forward_data + sign_ext_imm;
							forward_data <= forward_data + sign_ext_imm;
						end
						else
						begin
							alu_out <= a + sign_ext_imm;
							forward_data <= a + sign_ext_imm;
						end
					end

					//$display(" EX Calc ex: %h %h", a, sign_ext_imm);

					if (forward == 1)
					begin
						//$display("\nFWD REG %0d", fwd_reg);
						forward <= 0;
					end

					//$display("\nEX %2d, %2d, %2d", ex_reg0, ex_reg1, ex_reg2);
					//$display("\nID %2d, %2d, %2d", reg_rd_num0, reg_rd_num1, reg_rd_num2);
					if (ex_reg1 != 0 && (ex_reg1 == reg_rd_num0 || ex_reg1 == reg_rd_num1))
					begin
						forward <= 1;
						if (ex_reg1 == reg_rd_num0)
							fwd_reg <= 0;
						else
							fwd_reg <= 1;
					end

					if (ex_op == 'h2B) // sw
					begin
						//$write("\nprev b %h\n", b);
						st_en <= 1;
					end

					me_reg0 <= ex_reg0;
					me_reg1 <= ex_reg1;
					me_reg2 <= ex_reg2;
					me_op <= ex_op;
					me_funct <= ex_funct;
					me_pc <= ex_pc;

					// st_en = 1; uncomment to enable store to mem
					jump <= jump + 1;
					state <= id;
					pex += 1;		
				end
				me: begin
					//$write(" [ME %h %h %h %h] ", a, b, data_in, alu_out);		
					//$display("\nME %h %h", alu_out, data_in);
					
					st_en <= 0;

					if (me_funct == 'h21)
					begin // TODO : addu
						reg_wr_en <= 1;
						reg_wr_num <= me_reg2;
						reg_wr_data <= alu_out;
						if (ex_op == 'h2B && reg_wr_num != 29) // TODO : TEMP SOLUTION
						begin
							b <= alu_out;
						end
					end
					if (me_op == 'h09)
					begin // TODO : addiu
						reg_wr_en <= 1;
						reg_wr_num <= me_reg1;
						reg_wr_data <= alu_out;
						
						if (ex_op == 'h2B && reg_wr_num != 29) // TODO : TEMP SOLUTION
						begin
							b <= alu_out;
						end
						
						//$write("\n ME test write %h\n", alu_out);
					end
					if (me_op == 'h23) // lw
					begin
						reg_wr_num <= me_reg1;
						if (me_reg0 == 29) // Memory check
							reg_wr_data <= 'hxxxxxx;
						else
						begin
							if (forward == 1)
							begin
								reg_wr_data <= b;
							end
							else
								reg_wr_data <= data_in;
						end
						reg_wr_en <= 1;
					end

					wb_reg1 <= me_reg1;
					wb_op <= me_op;
					wb_funct <= me_funct;
					wb_pc <= me_pc;

					jump <= jump + 1;
					state <= ex;
					pme += 1;
				end
				wb: begin
					//$write(" [WB %h %h %h %h] ", a, b, data_in, alu_out);

					reg_wr_en <= 0;
					
					jump <= jump + 1;
					state <= me;
					pwb += 1;
				end
				default: begin
					reg_wr_en <= 0;
					state <= fetch;
				end
			endcase
	end

endmodule

src/memory.sv
module memory(
		input clk, input [31:0] addr, input [31:0] data_in,
		output logic [31:0] data_out, input [1:0] access_size, input rd_wr,
		output logic busy, input enable);
	`include "params.sv"

    reg[31:0] data [0:mem_depth/4-1];
    initial $readmemh(mem_file, data);

	wire[29:0] data_index = (addr - 32'h80020000) >> 2;
	logic [3:0] burst_count;
	logic [29:0] burst_addr;
	logic burst_rd_wr;
	assign busy = | burst_count;

	always @(posedge clk)
	begin
		if(enable) begin
			if(burst_count > 0) begin
				if(burst_rd_wr)
					data_out <= data[burst_addr];
				else
					data[burst_addr] <= data_in;
				burst_addr <= burst_addr + 1;
				burst_count <= burst_count - 1;
			end
			else begin
				if(rd_wr == 1) begin //read
					if(access_size==sz_byte)
						case(addr[1:0])
							// data is stored in big-endian order!!!
							3: data_out <=
								{24'hzzzzzz,data[data_index][7:0]};
							2: data_out <=
								{24'hzzzzzz,data[data_index][15:8]};
							1: data_out <=
								{24'hzzzzzz,data[data_index][23:16]};
							0: data_out <=
								{24'hzzzzzz,data[data_index][31:24]};
						endcase
					else
						data_out <= data[data_index];
				end
				else begin // write
					if(access_size==sz_byte)
						case(addr[1:0])
							// data is stored in big-endian order!!!
							3: data[data_index][7:0] <= data_in[7:0];
							2: data[data_index][15:8] <= data_in[7:0];
							1: data[data_index][23:16] <= data_in[7:0];
							0: data[data_index][31:24] <= data_in[7:0];
						endcase
					else
						data[data_index] <= data_in;
				end

				case(access_size)
					sz_byte: burst_count <= 0;
					sz_word: burst_count <= 0;
					sz_4word: burst_count <= 3;
					sz_8word: burst_count <= 7;
				endcase
				burst_addr <= data_index + 1;
				burst_rd_wr <= rd_wr;
			end
		end
		else begin
			burst_count <= 0;
			data_out <= 'Z;
		end
	end

endmodule

cpu_tb.sv
// this testbench loads SimpleAdd.x into the memory and executes the
// instructions found in it
module tb_SimpleAdd;
	`include "params.sv"
	logic clk;
	logic reset;

	// instruction memory / I-cache
	logic im_rw = 1; // 1=read,0=write
	logic [31:0] im_addr, im_dout;
	logic [1:0] im_access_sz = sz_word;
    memory imem(.clk(clk), .addr(im_addr), .data_out(im_dout),
		.access_size(im_access_sz), .rd_wr(im_rw), .enable(~reset));

	// data memory / D-cache
	logic dm_rw; // 1=read,0=write
	logic [31:0] dm_addr, dm_din, dm_dout;
	logic [1:0] dm_access_sz = sz_word;
    memory dmem(.clk(clk), .addr(dm_addr), .data_in(dm_din), .data_out(dm_dout),
		.access_size(dm_access_sz), .rd_wr(dm_rw), .enable(~reset));

	// mips processor
	// #(...) overrides parameters defined inside the module
	mips #(.pc_init(mem_start), .sp_init(mem_start+mem_depth), .ra_init(0))
		proc(.clk(clk), .reset(reset),
		.instr_addr(im_addr), .instr_in(im_dout),
		.data_addr(dm_addr), .data_in(dm_dout), .data_out(dm_din),
		.data_rd_wr(dm_rw));


	logic [31:0] pc_stack [5:0];

    initial begin
        clk = 1; forever #5 clk = ~clk;
    end

    initial begin
		reset <= 1;
		#10 reset <= 0;

		// for each instruction output the PC and show any store to memory
		// in ME stage or write to register in WB stage
		#1 ;
		
		for(int i=0; i<18; i++) begin
			#10 pc_stack[i % 5] <= im_addr;
			#40 if(tb_SimpleAdd.proc.reg_wr_en)
				$write("pc %h write %8h to r%1d\n",
					pc_stack[((i % 5) > 1)? ((i % 5) - 2) : 3 + (i % 5)], tb_SimpleAdd.proc.reg_wr_data,
					tb_SimpleAdd.proc.reg_wr_num);
			if(tb_SimpleAdd.proc.st_en)
				$write("pc %h store %8h at [%8h]\n",
					pc_stack[((i % 5) > 0)? ((i % 5) - 1) : 4], dm_din, dm_addr);
		end
		$write("pc %h\n",
			pc_stack[((18 % 5) > 1)? ((18 % 5) - 2) : 3 + (18 % 5)]);

		#10 $stop;
    end

    initial $dumpvars(0, tb_SimpleAdd); // creates waveform file

endmodule

dump.vcd
$date
	Thu Apr 11 08:24:47 2019
$end
$version
	Icarus Verilog
$end
$timescale
	1s
$end
$scope module tb_SimpleAdd $end
$var wire 32 ! im_dout [31:0] $end
$var wire 32 " im_addr [31:0] $end
$var wire 1 # dm_rw $end
$var wire 32 $ dm_dout [31:0] $end
$var wire 32 % dm_din [31:0] $end
$var wire 32 & dm_addr [31:0] $end
$var reg 1 ' clk $end
$var reg 2 ( dm_access_sz [1:0] $end
$var reg 2 ) im_access_sz [1:0] $end
$var reg 1 * im_rw $end
$var reg 1 + reset $end
$scope module dmem $end
$var wire 2 , access_size [1:0] $end
$var wire 1 ' clk $end
$var wire 1 - enable $end
$var wire 1 # rd_wr $end
$var wire 30 . data_index [29:0] $end
$var wire 32 / data_in [31:0] $end
$var wire 1 0 busy $end
$var wire 32 1 addr [31:0] $end
$var reg 30 2 burst_addr [29:0] $end
$var reg 4 3 burst_count [3:0] $end
$var reg 1 4 burst_rd_wr $end
$var reg 32 5 data_out [31:0] $end
$upscope $end
$scope module imem $end
$var wire 2 6 access_size [1:0] $end
$var wire 1 ' clk $end
$var wire 32 7 data_in [31:0] $end
$var wire 1 8 enable $end
$var wire 1 * rd_wr $end
$var wire 30 9 data_index [29:0] $end
$var wire 1 : busy $end
$var wire 32 ; addr [31:0] $end
$var reg 30 < burst_addr [29:0] $end
$var reg 4 = burst_count [3:0] $end
$var reg 1 > burst_rd_wr $end
$var reg 32 ? data_out [31:0] $end
$upscope $end
$scope module proc $end
$var wire 1 ' clk $end
$var wire 32 @ data_addr [31:0] $end
$var wire 32 A data_in [31:0] $end
$var wire 32 B data_out [31:0] $end
$var wire 1 # data_rd_wr $end
$var wire 32 C instr_in [31:0] $end
$var wire 1 + reset $end
$var wire 5 D reg_rd_num2 [4:0] $end
$var wire 5 E reg_rd_num1 [4:0] $end
$var wire 5 F reg_rd_num0 [4:0] $end
$var wire 32 G reg_rd_data1 [31:0] $end
$var wire 32 H reg_rd_data0 [31:0] $end
$var wire 32 I opcode [31:0] $end
$var wire 32 J instr_addr [31:0] $end
$var wire 32 K funct [31:0] $end
$var reg 32 L a [31:0] $end
$var reg 32 M alu_out [31:0] $end
$var reg 32 N b [31:0] $end
$var reg 32 O ex_funct [31:0] $end
$var reg 32 P ex_op [31:0] $end
$var reg 32 Q ex_pc [31:0] $end
$var reg 5 R ex_reg0 [4:0] $end
$var reg 5 S ex_reg1 [4:0] $end
$var reg 5 T ex_reg2 [4:0] $end
$var reg 2 U forward [1:0] $end
$var reg 32 V forward_data [31:0] $end
$var reg 1 W fwd_reg $end
$var reg 32 X idle_ctrl [31:0] $end
$var reg 32 Y ir [31:0] $end
$var reg 32 Z jump [31:0] $end
$var reg 32 [ me_funct [31:0] $end
$var reg 32 \ me_op [31:0] $end
$var reg 32 ] me_pc [31:0] $end
$var reg 5 ^ me_reg0 [4:0] $end
$var reg 5 _ me_reg1 [4:0] $end
$var reg 5 ` me_reg2 [4:0] $end
$var reg 32 a pc [31:0] $end
$var reg 32 b reg_wr_data [31:0] $end
$var reg 1 c reg_wr_en $end
$var reg 5 d reg_wr_num [4:0] $end
$var reg 32 e sign_ext_imm [31:0] $end
$var reg 1 f st_en $end
$var reg 32 g wb_funct [31:0] $end
$var reg 32 h wb_op [31:0] $end
$var reg 32 i wb_pc [31:0] $end
$var reg 5 j wb_reg1 [4:0] $end
$var integer 32 k pex [31:0] $end
$var integer 32 l pfetch [31:0] $end
$var integer 32 m pid [31:0] $end
$var integer 32 n pme [31:0] $end
$var integer 32 o pwb [31:0] $end
$var integer 32 p state [31:0] $end
$scope module regs $end
$var wire 1 ' clk $end
$var wire 5 q rd0_num [4:0] $end
$var wire 5 r rd1_num [4:0] $end
$var wire 1 + reset $end
$var wire 32 s wr_data [31:0] $end
$var wire 1 c wr_en $end
$var wire 5 t wr_num [4:0] $end
$var wire 32 u rd1_data [31:0] $end
$var wire 32 v rd0_data [31:0] $end
$upscope $end
$upscope $end
$scope begin $ivl_for_loop0 $end
$var integer 32 w i [31:0] $end
$upscope $end
$upscope $end
$enddefinitions $end
#0
$dumpvars
b0 w
bx v
bx u
bx t
bx s
bx r
bx q
b0 p
b0 o
b0 n
b0 m
b0 l
b0 k
bx j
bx i
bx h
bx g
xf
bx e
bx d
0c
bx b
b10000000000000100000000000000000 a
bx `
bx _
bx ^
bx ]
bx \
bx [
b1 Z
bx Y
b101 X
xW
bx V
b0 U
bx T
bx S
bx R
bx Q
bx P
bx O
bx N
bx M
bx L
b0xxxxxx K
b10000000000000100000000000000000 J
b0xxxxxx I
bx H
bx G
bx F
bx E
bx D
bz C
bx B
bz A
bx @
bz ?
x>
b0 =
bx <
b10000000000000100000000000000000 ;
0:
b0 9
08
bz 7
b1 6
bz 5
x4
b0 3
bx 2
bx 1
00
bx /
bx .
0-
b1 ,
1+
1*
b1 )
b1 (
1'
bx &
bx %
bz $
x#
b10000000000000100000000000000000 "
bz !
$end
#5
0'
#10
1-
18
0+
1'
#15
0'
#20
1>
b1 <
b100111101111011111111111101000 !
b100111101111011111111111101000 ?
b100111101111011111111111101000 C
b1 p
1'
#25
0'
#30
b100 X
1'
#35
0'
#40
b11 X
1'
#45
0'
#50
b10 p
b10 X
1'
#55
0'
#60
b1 9
b10000000000100100000000000000000 H
b10000000000100100000000000000000 v
b10000000000100100000000000000000 G
b10000000000100100000000000000000 u
b11101 F
b11101 q
b11101 E
b11101 r
b11111 D
b1001 I
b101000 K
b11 p
b10000000000000100000000000000100 "
b10000000000000100000000000000100 ;
b10000000000000100000000000000100 J
b10000000000000100000000000000100 a
b100111101111011111111111101000 Y
b1 l
1'
#61
b1 w
#65
0'
#70
b10 <
b10101111101111100000000000010100 !
b10101111101111100000000000010100 ?
b10101111101111100000000000010100 C
b10 p
b10 Z
b10000000000000100000000000000100 Q
b11111 T
b11101 S
b11101 R
b101000 O
b1001 P
b11111111111111111111111111101000 e
b10000000000100100000000000000000 %
b10000000000100100000000000000000 /
b10000000000100100000000000000000 B
b10000000000100100000000000000000 N
b10000000000100100000000000000000 L
b1 m
1'
#75
0'
#80
b10 9
bx G
bx u
b11110 E
b11110 r
b0 D
b101011 I
b10100 K
b1 p
b10000000000000100000000000001000 "
b10000000000000100000000000001000 ;
b10000000000000100000000000001000 J
b10000000000000100000000000001000 a
b10101111101111100000000000010100 Y
b10 l
1'
#85
0'
#90
b11 <
b11101000001111000000100001 !
b11101000001111000000100001 ?
b11101000001111000000100001 C
b1 X
1'
#95
0'
#100
b0 X
1'
#105
0'
#110
b100 p
b11111111111111111111111111111111 X
1'
#111
b10 w
#115
0'
#120
b111111111111111010 .
b11 p
b11 Z
b10000000000000100000000000000100 ]
b101000 [
b1001 \
b11111 `
b11101 _
b11101 ^
0W
b1 U
b10000000000100011111111111101000 V
b10000000000100011111111111101000 &
b10000000000100011111111111101000 1
b10000000000100011111111111101000 @
b10000000000100011111111111101000 M
b1 k
1'
#125
0'
#130
b111111111111111011 2
b10 p
b100 Z
b10000000000000100000000000001000 Q
b0 T
b11110 S
b10100 O
b101011 P
b10100 e
bx %
bx /
bx B
bx N
b10 m
1'
#135
0'
#140
b11 9
b0 G
b0 u
b0 E
b0 r
b11110 D
b0 I
b100001 K
b101 p
b10000000000000100000000000001100 "
b10000000000000100000000000001100 ;
b10000000000000100000000000001100 J
b10000000000000100000000000001100 a
b11101000001111000000100001 Y
b11 l
1'
#145
0'
#150
1#
b100 <
b100100000000100000000000000011 !
b100100000000100000000000000011 ?
b100100000000100000000000000011 C
b100 p
b101 Z
b10000000000000100000000000000100 i
b101000 g
b1001 h
b11101 j
b10000000000100011111111111101000 b
b10000000000100011111111111101000 s
b11101 d
b11101 t
1c
0f
b1 n
1'
#155
0'
#160
b111111111111111111 .
0#
b10000000000100011111111111101000 H
b10000000000100011111111111101000 v
14
bx $
bx 5
bx A
b11 p
b110 Z
b10000000000000100000000000001000 ]
b10100 [
b101011 \
b0 `
b11110 _
1f
b0 U
b10000000000100011111111111111100 V
b10000000000100011111111111111100 &
b10000000000100011111111111111100 1
b10000000000100011111111111111100 @
b10000000000100011111111111111100 M
b10 k
1'
#161
b11 w
#165
0'
#170
04
b1000000000000000000 2
b10 p
b111 Z
b10000000000000100000000000001100 Q
b11110 T
b0 S
b100001 O
b0 P
b11111111111111111111000000100001 e
b0 %
b0 /
b0 B
b0 N
b10000000000100011111111111101000 L
b11 m
1'
#175
0'
#180
b100 9
b0 H
b0 v
bx G
bx u
b0 F
b0 q
b10 E
b10 r
b0 D
b1001 I
b11 K
b110 p
b10000000000000100000000000010000 "
b10000000000000100000000000010000 ;
b10000000000000100000000000010000 J
b10000000000000100000000000010000 a
b100100000000100000000000000011 Y
b100 l
1'
#185
0'
#190
b101 <
b10101111110000100000000000000000 !
b10101111110000100000000000000000 ?
b10101111110000100000000000000000 C
b101 p
b1000 Z
0c
b1 o
1'
#195
0'
#200
1#
b100 p
b1001 Z
b10000000000000100000000000001000 i
b10100 g
b101011 h
b11110 j
0f
b10 n
1'
#205
0'
#210
b111111111111111010 .
14
b0 $
b0 5
b0 A
b11 p
b1010 Z
b10000000000000100000000000001100 ]
b100001 [
b0 \
b11110 `
b0 _
b10000000000100011111111111101000 V
b10000000000100011111111111101000 &
b10000000000100011111111111101000 1
b10000000000100011111111111101000 @
b10000000000100011111111111101000 M
b11 k
1'
#211
b100 w
#215
0'
#220
b111111111111111011 2
bx $
bx 5
bx A
b10 p
b1011 Z
b10000000000000100000000000010000 Q
b0 T
b10 S
b0 R
b11 O
b1001 P
b11 e
bx %
bx /
bx B
bx N
b0 L
b100 m
1'
#225
0'
#230
b101 9
bx H
bx v
b11110 F
b11110 q
b101011 I
b0 K
b110 p
b10000000000000100000000000010100 "
b10000000000000100000000000010100 ;
b10000000000000100000000000010100 J
b10000000000000100000000000010100 a
b10101111110000100000000000000000 Y
b101 l
1'
#235
0'
#240
b110 <
b100100000000100000000000000010 !
b100100000000100000000000000010 ?
b100100000000100000000000000010 C
b101 p
b1100 Z
b10 o
1'
#245
0'
#250
b100 p
b1101 Z
b10000000000000100000000000001100 i
b100001 g
b0 h
b0 j
b11110 d
b11110 t
1c
b11 n
1'
#255
0'
#260
b11111111111111000000000000000 .
b10000000000100011111111111101000 H
b10000000000100011111111111101000 v
b11 p
b1110 Z
b10000000000000100000000000010000 ]
b11 [
b1001 \
b0 `
b10 _
b0 ^
1W
b1 U
b11 V
b11 &
b11 1
b11 @
b11 M
b100 k
1'
#261
b101 w
#265
0'
#270
b11111111111111000000000000001 2
b10 p
b1111 Z
b10000000000000100000000000010100 Q
b11110 R
b0 O
b101011 P
b0 e
b10000000000100011111111111101000 L
b101 m
1'
#275
0'
#280
b110 9
b0 H
b0 v
b0 F
b0 q
b1001 I
b10 K
b110 p
b10000000000000100000000000011000 "
b10000000000000100000000000011000 ;
b10000000000000100000000000011000 J
b10000000000000100000000000011000 a
b100100000000100000000000000010 Y
b110 l
1'
#285
0'
#290
b111 <
b10101111110000100000000000000100 !
b10101111110000100000000000000100 ?
b10101111110000100000000000000100 C
b101 p
b10000 Z
0c
b11 o
1'
#295
0'
#300
b100 p
b10001 Z
b10000000000000100000000000010000 i
b11 g
b1001 h
b10 j
b11 %
b11 /
b11 B
b11 N
b11 b
b11 s
b10 d
b10 t
1c
b100 n
1'
#305
0'
#310
b111111111111111010 .
b11 G
b11 u
0#
b11 p
b10010 Z
b10000000000000100000000000010100 ]
b0 [
b101011 \
b11110 ^
1f
b1 U
b10000000000100011111111111101000 V
b10000000000100011111111111101000 &
b10000000000100011111111111101000 1
b10000000000100011111111111101000 @
b10000000000100011111111111101000 M
b101 k
1'
#311
b110 w
#315
0'
#320
04
b111111111111111011 2
b10 p
b10011 Z
b10000000000000100000000000011000 Q
b0 R
b10 O
b1001 P
b10 e
b0 L
b110 m
1'
#325
0'
#330
b111 9
b10000000000100011111111111101000 H
b10000000000100011111111111101000 v
b11110 F
b11110 q
b101011 I
b100 K
b110 p
b10000000000000100000000000011100 "
b10000000000000100000000000011100 ;
b10000000000000100000000000011100 J
b10000000000000100000000000011100 a
b10101111110000100000000000000100 Y
b111 l
1'
#335
0'
#340
b1000 <
b10101111110000000000000000001000 !
b10101111110000000000000000001000 ?
b10101111110000000000000000001000 C
b101 p
b10100 Z
0c
b100 o
1'
#345
0'
#350
1#
b100 p
b10101 Z
b10000000000000100000000000010100 i
b0 g
b101011 h
0f
b101 n
1'
#355
0'
#360
b11111111111111000000000000000 .
14
b11 $
b11 5
b11 A
b11 p
b10110 Z
b10000000000000100000000000011000 ]
b10 [
b1001 \
b0 ^
b1 U
b10 V
b10 &
b10 1
b10 @
b10 M
b110 k
1'
#361
b111 w
#365
0'
#370
b11111111111111000000000000001 2
bx $
bx 5
bx A
b10 p
b10111 Z
b10000000000000100000000000011100 Q
b11110 R
b100 O
b101011 P
b100 e
b10000000000100011111111111101000 L
b111 m
1'
#375
0'
#380
b1000 9
b0 G
b0 u
b0 E
b0 r
b1000 K
b110 p
b10000000000000100000000000100000 "
b10000000000000100000000000100000 ;
b10000000000000100000000000100000 J
b10000000000000100000000000100000 a
b10101111110000000000000000001000 Y
b1000 l
1'
#385
0'
#390
b1001 <
b10001111110000110000000000000000 !
b10001111110000110000000000000000 ?
b10001111110000110000000000000000 C
b101 p
b11000 Z
b101 o
1'
#395
0'
#400
b100 p
b11001 Z
b10000000000000100000000000011000 i
b10 g
b1001 h
b10 %
b10 /
b10 B
b10 N
b10 b
b10 s
1c
b110 n
1'
#405
0'
#410
b111111111111111011 .
0#
b11 p
b11010 Z
b10000000000000100000000000011100 ]
b100 [
b101011 \
b11110 ^
1f
b0 U
b10000000000100011111111111101100 V
b10000000000100011111111111101100 &
b10000000000100011111111111101100 1
b10000000000100011111111111101100 @
b10000000000100011111111111101100 M
b111 k
1'
#411
b1000 w
#415
0'
#420
04
b111111111111111100 2
b10 p
b11011 Z
b10000000000000100000000000100000 Q
b0 S
b1000 O
b1000 e
b0 %
b0 /
b0 B
b0 N
b1000 m
1'
#425
0'
#430
b1001 9
bx G
bx u
b11 E
b11 r
b100011 I
b0 K
b110 p
b10000000000000100000000000100100 "
b10000000000000100000000000100100 ;
b10000000000000100000000000100100 J
b10000000000000100000000000100100 a
b10001111110000110000000000000000 Y
b1001 l
1'
#435
0'
#440
b1010 <
b10001111110000100000000000000100 !
b10001111110000100000000000000100 ?
b10001111110000100000000000000100 C
b101 p
b11100 Z
0c
b110 o
1'
#445
0'
#450
1#
b100 p
b11101 Z
b10000000000000100000000000011100 i
b100 g
b101011 h
0f
b111 n
1'
#455
0'
#460
b111111111111111100 .
0#
14
b0 $
b0 5
b0 A
b11 p
b11110 Z
b10000000000000100000000000100000 ]
b1000 [
b0 _
1f
b10000000000100011111111111110000 V
b10000000000100011111111111110000 &
b10000000000100011111111111110000 1
b10000000000100011111111111110000 @
b10000000000100011111111111110000 M
b1000 k
1'
#461
b1001 w
#465
0'
#470
04
b111111111111111101 2
b10 p
b11111 Z
b10000000000000100000000000100100 Q
b11 S
b0 O
b100011 P
b0 e
bx %
bx /
bx B
bx N
b1001 m
1'
#475
0'
#480
b1010 9
b10 G
b10 u
b10 E
b10 r
b100 K
b110 p
b10000000000000100000000000101000 "
b10000000000000100000000000101000 ;
b10000000000000100000000000101000 J
b10000000000000100000000000101000 a
b10001111110000100000000000000100 Y
b1010 l
1'
#485
0'
#490
b1011 <
b11000100001000000100001 !
b11000100001000000100001 ?
b11000100001000000100001 C
b101 p
b100000 Z
b111 o
1'
#495
0'
#500
1#
b100 p
b100001 Z
b10000000000000100000000000100000 i
b1000 g
b0 j
0f
b1000 n
1'
#505
0'
#510
b111111111111111010 .
14
bx $
bx 5
bx A
b11 p
b100010 Z
b10000000000000100000000000100100 ]
b0 [
b100011 \
b11 _
b10000000000100011111111111101000 V
b10000000000100011111111111101000 &
b10000000000100011111111111101000 1
b10000000000100011111111111101000 @
b10000000000100011111111111101000 M
b1001 k
1'
#511
b1010 w
#515
0'
#520
b111111111111111011 2
b11 $
b11 5
b11 A
b10 p
b100011 Z
b10000000000000100000000000101000 Q
b10 S
b100 O
b100 e
b10 %
b10 /
b10 B
b10 N
b1010 m
1'
#525
0'
#530
b1011 9
bx H
bx v
b11 F
b11 q
b10 D
b0 I
b100001 K
b110 p
b10000000000000100000000000101100 "
b10000000000000100000000000101100 ;
b10000000000000100000000000101100 J
b10000000000000100000000000101100 a
b11000100001000000100001 Y
b1011 l
1'
#535
0'
#540
b1100 <
b10101111110000100000000000001000 !
b10101111110000100000000000001000 ?
b10101111110000100000000000001000 C
b101 p
b100100 Z
b1000 o
1'
#545
0'
#550
b100 p
b100101 Z
b10000000000000100000000000100100 i
b0 g
b100011 h
b11 j
1c
b11 b
b11 s
b11 d
b11 t
b1001 n
1'
#555
0'
#560
b111111111111111011 .
b11 H
b11 v
b11 p
b100110 Z
b10000000000000100000000000101000 ]
b100 [
b10 _
b1 U
b10000000000100011111111111101100 V
b10000000000100011111111111101100 &
b10000000000100011111111111101100 1
b10000000000100011111111111101100 @
b10000000000100011111111111101100 M
b1010 k
1'
#561
b1011 w
#565
0'
#570
b111111111111111100 2
b0 $
b0 5
b0 A
b10 p
b100111 Z
b10000000000000100000000000101100 Q
b10 T
b11 R
b100001 O
b0 P
b1000000100001 e
b11 L
b1011 m
1'
#575
0'
#580
b1100 9
b10000000000100011111111111101000 H
b10000000000100011111111111101000 v
b11110 F
b11110 q
b0 D
b101011 I
b1000 K
b110 p
b10000000000000100000000000110000 "
b10000000000000100000000000110000 ;
b10000000000000100000000000110000 J
b10000000000000100000000000110000 a
b10101111110000100000000000001000 Y
b1100 l
1'
#585
0'
#590
b1101 <
b10001111110000100000000000001000 !
b10001111110000100000000000001000 ?
b10001111110000100000000000001000 C
b101 p
b101000 Z
0c
b1001 o
1'
#595
0'
#600
b100 p
b101001 Z
b10000000000000100000000000101000 i
b100 g
b10 j
1c
b10 b
b10 s
b10 d
b10 t
b1010 n
1'
#605
0'
#610
b11111111111111000000000000001 .
b11 p
b101010 Z
b10000000000000100000000000101100 ]
b100001 [
b0 \
b10 `
b11 ^
b1 U
b101 V
b101 &
b101 1
b101 @
b101 M
b1011 k
1'
#611
b1100 w
#615
0'
