src/params.sv
    parameter mem_file = "SimpleAdd.x";
	parameter [31:0] mem_start = 32'h80020000;
	parameter mem_depth = 2**20; // 1 MB
	typedef enum { sz_byte, sz_word, sz_4word, sz_8word } mem_access_sizes;

src/regfile.sv
module regfile(
		input [4:0] wr_num, input [31:0] wr_data, input wr_en,
		input [4:0] rd0_num, output [31:0] rd0_data,
		input [4:0] rd1_num, output [31:0] rd1_data,
		input clk, reset);

	parameter [31:0] sp_init = 0;
	parameter [31:0] ra_init = 0;

    reg[31:0] data [1:31]; // general-purpose registers r1-r31 (r0===0)

	always @(posedge clk or posedge reset)
	if(reset) begin
		data[29] <= sp_init;
		data[31] <= ra_init;
	end
	else begin
        if(wr_en && wr_num!=0) data[wr_num] <= wr_data;
	end

   	assign rd0_data = (rd0_num!=0) ? data[rd0_num] : 32'h00000000;
   	assign rd1_data = (rd1_num!=0) ? data[rd1_num] : 32'h00000000;

endmodule

src/mips.sv
// this is a mips module that can only execute the addiu instruction
module mips(
	// port list
	input clk, reset,
	output [31:0] instr_addr,
	input [31:0] instr_in,
	output [31:0] data_addr,
	input [31:0] data_in,
	output logic [31:0] data_out,
	output data_rd_wr);

	// parameters overridden in testbench
	parameter [31:0] pc_init = 0;
	parameter [31:0] sp_init = 0;
	parameter [31:0] ra_init = 0;

	// IF signals
	logic [31:0] pc;
	assign instr_addr = pc;
	logic [31:0] ir;

	// ID signals
    logic [4:0] reg_rd_num0, reg_rd_num1, reg_rd_num2;
	logic [31:0] opcode, funct;
    wire [31:0] reg_rd_data0, reg_rd_data1;
	assign reg_rd_num0 = ir[25:21];
	assign reg_rd_num1 = ir[20:16];
	assign reg_rd_num2 = ir[15:11];
	assign opcode = ir[31:26];
	assign funct = ir[5:0];

	// EX signals
	logic [31:0] a, b, sign_ext_imm;
	logic [31:0] alu_out;

	// ME signals
	logic st_en;
	assign data_out = b;
	assign data_rd_wr = ~st_en;
	assign data_addr = alu_out;

	// WD signals
    logic [4:0] reg_wr_num;
    logic [31:0] reg_wr_data;
    logic reg_wr_en;

	enum { init, fetch, id, ex, me, wb } state;

	// register file
    regfile #(.sp_init(sp_init), .ra_init(ra_init)) regs(
		.wr_num(reg_wr_num), .wr_data(reg_wr_data), .wr_en(reg_wr_en),
        .rd0_num(reg_rd_num0), .rd0_data(reg_rd_data0),
		.rd1_num(reg_rd_num1), .rd1_data(reg_rd_data1),
        .clk(clk), .reset(reset));

	always @(posedge clk or posedge reset) begin
		if(reset) begin
			reg_wr_en <= 0;
			pc <= pc_init;
			state <= init;
		end
		else
			case(state)
				init: begin
					// this state is needed since we have to wait for
					// memory to produce the first instruction after reset
					state <= fetch;
				end
				fetch: begin		
					if (opcode == 'h23) // lw
					begin
						reg_wr_en <= 0;
					end

					ir <= instr_in;
					pc <= pc + 4;
					state <= id;
				end
				id: begin
					a <= reg_rd_data0;
					b <= reg_rd_data1;
					sign_ext_imm <= {{16{ir[15]}},ir[15:0]};
					state <= ex;
				end
				ex: begin
					//$write(" a: %h, b %h, imm %h ", a, b, sign_ext_imm);
					
					if (opcode == 'h0) // add*
						alu_out <= a + b;
					else
						alu_out <= a + sign_ext_imm;

					if (opcode == 'h2B) // sw
					begin
						st_en <= 1;
					end

					// st_en = 1; uncomment to enable store to mem
					state <= me;
				end
				me: begin
					st_en <= 0;
					reg_wr_num <= ir[20:16];
					
					if (ir[5:0] == 'h21)
					begin // TODO : addiu
						reg_wr_en <= 1;
						reg_wr_num <= ir[15:11];
						reg_wr_data <= alu_out;
					end
					if (ir[31:26] == 'h09)
					begin
						reg_wr_en <= 1;
						reg_wr_num <= ir[20:16];
						reg_wr_data <= alu_out;
					end

					if (opcode == 'h23) // lw
					begin
						st_en <= 0;
					end
					state <= wb;
				end
				wb: begin
					if (opcode == 'h23) // lw
					begin
						reg_wr_data <= data_in;
						reg_wr_en <= 1;
						$write(" write %h to r%1d\n", data_in, ir[20:16]);
					end
					else
						reg_wr_en <= 0;
					
					state <= fetch;
				end
				default: begin
					reg_wr_en <= 0;
					state <= fetch;
				end
			endcase
	end

endmodule

src/memory.sv
module memory(
		input clk, input [31:0] addr, input [31:0] data_in,
		output logic [31:0] data_out, input [1:0] access_size, input rd_wr,
		output logic busy, input enable);
	`include "params.sv"

    reg[31:0] data [0:mem_depth/4-1];
    initial $readmemh(mem_file, data);

	wire[29:0] data_index = (addr - 32'h80020000) >> 2;
	logic [3:0] burst_count;
	logic [29:0] burst_addr;
	logic burst_rd_wr;
	assign busy = | burst_count;

	always @(posedge clk)
	begin
		if(enable) begin
			if(burst_count > 0) begin
				if(burst_rd_wr)
					data_out <= data[burst_addr];
				else
					data[burst_addr] <= data_in;
				burst_addr <= burst_addr + 1;
				burst_count <= burst_count - 1;
			end
			else begin
				if(rd_wr == 1) begin //read
					if(access_size==sz_byte)
						case(addr[1:0])
							// data is stored in big-endian order!!!
							3: data_out <=
								{24'hzzzzzz,data[data_index][7:0]};
							2: data_out <=
								{24'hzzzzzz,data[data_index][15:8]};
							1: data_out <=
								{24'hzzzzzz,data[data_index][23:16]};
							0: data_out <=
								{24'hzzzzzz,data[data_index][31:24]};
						endcase
					else
						data_out <= data[data_index];
				end
				else begin // write
					if(access_size==sz_byte)
						case(addr[1:0])
							// data is stored in big-endian order!!!
							3: data[data_index][7:0] <= data_in[7:0];
							2: data[data_index][15:8] <= data_in[7:0];
							1: data[data_index][23:16] <= data_in[7:0];
							0: data[data_index][31:24] <= data_in[7:0];
						endcase
					else
						data[data_index] <= data_in;
				end

				case(access_size)
					sz_byte: burst_count <= 0;
					sz_word: burst_count <= 0;
					sz_4word: burst_count <= 3;
					sz_8word: burst_count <= 7;
				endcase
				burst_addr <= data_index + 1;
				burst_rd_wr <= rd_wr;
			end
		end
		else begin
			burst_count <= 0;
			data_out <= 'Z;
		end
	end

endmodule

src/p2_tb.sv
// this testbench loads SimpleAdd.x into the memory and executes the
// instructions found in it
module tb_SimpleAdd;
	`include "params.sv"
	logic clk;
	logic reset;

	// instruction memory / I-cache
	logic im_rw = 1; // 1=read,0=write
	logic [31:0] im_addr, im_dout;
	logic [1:0] im_access_sz = sz_word;
    memory imem(.clk(clk), .addr(im_addr), .data_out(im_dout),
		.access_size(im_access_sz), .rd_wr(im_rw), .enable(~reset));

	// data memory / D-cache
	logic dm_rw; // 1=read,0=write
	logic [31:0] dm_addr, dm_din, dm_dout;
	logic [1:0] dm_access_sz = sz_word;
    memory dmem(.clk(clk), .addr(dm_addr), .data_in(dm_din), .data_out(dm_dout),
		.access_size(dm_access_sz), .rd_wr(dm_rw), .enable(~reset));

	// mips processor
	// #(...) overrides parameters defined inside the module
	mips #(.pc_init(mem_start), .sp_init(mem_start+mem_depth), .ra_init(0))
		proc(.clk(clk), .reset(reset),
		.instr_addr(im_addr), .instr_in(im_dout),
		.data_addr(dm_addr), .data_in(dm_dout), .data_out(dm_din),
		.data_rd_wr(dm_rw));
 
    initial begin
        clk = 1; forever #5 clk = ~clk;
    end

    initial begin
		reset <= 1;
		#10 reset <= 0;

		// for each instruction output the PC and show any store to memory
		// in ME stage or write to register in WB stage
		#1 ;
		for(int i=0; i<17; i++) begin
			#10 $write("pc %8h", im_addr);
			#30 if(tb_SimpleAdd.proc.st_en)
				$write(" store %8h at [%8h]\n", dm_din, dm_addr);
			#10 if(tb_SimpleAdd.proc.reg_wr_en)
				$write(" write %8h to r%1d\n", tb_SimpleAdd.proc.reg_wr_data,
					tb_SimpleAdd.proc.reg_wr_num);
			//$write("\n");
		end
		$write("\n");
		#10 $stop;
    end

    initial $dumpvars(0, tb_SimpleAdd); // creates waveform file

endmodule

src/dump.vcd
$date
	Sun Mar 24 01:52:51 2019
$end
$version
	Icarus Verilog
$end
$timescale
	1s
$end
$scope module tb_SimpleAdd $end
$var wire 32 ! im_dout [31:0] $end
$var wire 32 " im_addr [31:0] $end
$var wire 1 # dm_rw $end
$var wire 32 $ dm_dout [31:0] $end
$var wire 32 % dm_din [31:0] $end
$var wire 32 & dm_addr [31:0] $end
$var reg 1 ' clk $end
$var reg 2 ( dm_access_sz [1:0] $end
$var reg 2 ) im_access_sz [1:0] $end
$var reg 1 * im_rw $end
$var reg 1 + reset $end
$scope module dmem $end
$var wire 2 , access_size [1:0] $end
$var wire 1 ' clk $end
$var wire 1 - enable $end
$var wire 1 # rd_wr $end
$var wire 30 . data_index [29:0] $end
$var wire 32 / data_in [31:0] $end
$var wire 1 0 busy $end
$var wire 32 1 addr [31:0] $end
$var reg 30 2 burst_addr [29:0] $end
$var reg 4 3 burst_count [3:0] $end
$var reg 1 4 burst_rd_wr $end
$var reg 32 5 data_out [31:0] $end
$upscope $end
$scope module imem $end
$var wire 2 6 access_size [1:0] $end
$var wire 1 ' clk $end
$var wire 32 7 data_in [31:0] $end
$var wire 1 8 enable $end
$var wire 1 * rd_wr $end
$var wire 30 9 data_index [29:0] $end
$var wire 1 : busy $end
$var wire 32 ; addr [31:0] $end
$var reg 30 < burst_addr [29:0] $end
$var reg 4 = burst_count [3:0] $end
$var reg 1 > burst_rd_wr $end
$var reg 32 ? data_out [31:0] $end
$upscope $end
$scope module proc $end
$var wire 1 ' clk $end
$var wire 32 @ data_addr [31:0] $end
$var wire 32 A data_in [31:0] $end
$var wire 32 B data_out [31:0] $end
$var wire 1 # data_rd_wr $end
$var wire 32 C instr_in [31:0] $end
$var wire 1 + reset $end
$var wire 5 D reg_rd_num2 [4:0] $end
$var wire 5 E reg_rd_num1 [4:0] $end
$var wire 5 F reg_rd_num0 [4:0] $end
$var wire 32 G reg_rd_data1 [31:0] $end
$var wire 32 H reg_rd_data0 [31:0] $end
$var wire 32 I opcode [31:0] $end
$var wire 32 J instr_addr [31:0] $end
$var wire 32 K funct [31:0] $end
$var reg 32 L a [31:0] $end
$var reg 32 M alu_out [31:0] $end
$var reg 32 N b [31:0] $end
$var reg 32 O ir [31:0] $end
$var reg 32 P pc [31:0] $end
$var reg 32 Q reg_wr_data [31:0] $end
$var reg 1 R reg_wr_en $end
$var reg 5 S reg_wr_num [4:0] $end
$var reg 32 T sign_ext_imm [31:0] $end
$var reg 1 U st_en $end
$var integer 32 V state [31:0] $end
$scope module regs $end
$var wire 1 ' clk $end
$var wire 5 W rd0_num [4:0] $end
$var wire 5 X rd1_num [4:0] $end
$var wire 1 + reset $end
$var wire 32 Y wr_data [31:0] $end
$var wire 1 R wr_en $end
$var wire 5 Z wr_num [4:0] $end
$var wire 32 [ rd1_data [31:0] $end
$var wire 32 \ rd0_data [31:0] $end
$upscope $end
$upscope $end
$scope begin $ivl_for_loop0 $end
$var integer 32 ] i [31:0] $end
$upscope $end
$upscope $end
$enddefinitions $end
#0
$dumpvars
b0 ]
bx \
bx [
bx Z
bx Y
bx X
bx W
b0 V
xU
bx T
bx S
0R
bx Q
b10000000000000100000000000000000 P
bx O
bx N
bx M
bx L
b0xxxxxx K
b10000000000000100000000000000000 J
b0xxxxxx I
bx H
bx G
bx F
bx E
bx D
bz C
bx B
bz A
bx @
bz ?
x>
b0 =
bx <
b10000000000000100000000000000000 ;
0:
b0 9
08
bz 7
b1 6
bz 5
x4
b0 3
bx 2
bx 1
00
bx /
bx .
0-
b1 ,
1+
1*
b1 )
b1 (
1'
bx &
bx %
bz $
x#
b10000000000000100000000000000000 "
bz !
$end
#5
0'
#10
1-
18
0+
1'
#15
0'
#20
1>
b1 <
b100111101111011111111111101000 !
b100111101111011111111111101000 ?
b100111101111011111111111101000 C
b1 V
1'
#25
0'
#30
b1 9
b10000000000100100000000000000000 H
b10000000000100100000000000000000 \
b10000000000100100000000000000000 G
b10000000000100100000000000000000 [
b11101 F
b11101 W
b11101 E
b11101 X
b11111 D
b1001 I
b101000 K
b10 V
b10000000000000100000000000000100 "
b10000000000000100000000000000100 ;
b10000000000000100000000000000100 J
b10000000000000100000000000000100 P
b100111101111011111111111101000 O
1'
#35
0'
#40
b10 <
b10101111101111100000000000010100 !
b10101111101111100000000000010100 ?
b10101111101111100000000000010100 C
b11 V
b11111111111111111111111111101000 T
b10000000000100100000000000000000 %
b10000000000100100000000000000000 /
b10000000000100100000000000000000 B
b10000000000100100000000000000000 N
b10000000000100100000000000000000 L
1'
#45
0'
#50
b111111111111111010 .
b100 V
b10000000000100011111111111101000 &
b10000000000100011111111111101000 1
b10000000000100011111111111101000 @
b10000000000100011111111111101000 M
1'
#55
0'
#60
1#
b111111111111111011 2
b101 V
b10000000000100011111111111101000 Q
b10000000000100011111111111101000 Y
1R
b11101 S
b11101 Z
0U
1'
#61
b1 ]
#65
0'
#70
b10000000000100011111111111101000 H
b10000000000100011111111111101000 \
b10000000000100011111111111101000 G
b10000000000100011111111111101000 [
14
b10000000000100100000000000000000 $
b10000000000100100000000000000000 5
b10000000000100100000000000000000 A
b1 V
0R
1'
#75
0'
#80
b10 9
bx G
bx [
b11110 E
b11110 X
b0 D
b101011 I
b10100 K
b10 V
b10000000000000100000000000001000 "
b10000000000000100000000000001000 ;
b10000000000000100000000000001000 J
b10000000000000100000000000001000 P
b10101111101111100000000000010100 O
1'
#85
0'
#90
b11 <
b11101000001111000000100001 !
b11101000001111000000100001 ?
b11101000001111000000100001 C
b11 V
b10100 T
bx %
bx /
bx B
bx N
b10000000000100011111111111101000 L
1'
#95
0'
#100
b111111111111111111 .
0#
b100 V
1U
b10000000000100011111111111111100 &
b10000000000100011111111111111100 1
b10000000000100011111111111111100 @
b10000000000100011111111111111100 M
1'
#105
0'
#110
1#
04
b1000000000000000000 2
b101 V
b11110 S
b11110 Z
0U
1'
#111
b10 ]
#115
0'
#120
14
bx $
bx 5
bx A
b1 V
1'
#125
0'
#130
b11 9
b0 G
b0 [
b0 E
b0 X
b11110 D
b0 I
b100001 K
b10 V
b10000000000000100000000000001100 "
b10000000000000100000000000001100 ;
b10000000000000100000000000001100 J
b10000000000000100000000000001100 P
b11101000001111000000100001 O
1'
#135
0'
#140
b100 <
b100100000000100000000000000011 !
b100100000000100000000000000011 ?
b100100000000100000000000000011 C
b11 V
b11111111111111111111000000100001 T
b0 %
b0 /
b0 B
b0 N
1'
#145
0'
#150
b111111111111111010 .
b100 V
b10000000000100011111111111101000 &
b10000000000100011111111111101000 1
b10000000000100011111111111101000 @
b10000000000100011111111111101000 M
1'
#155
0'
#160
b111111111111111011 2
b10000000000100100000000000000000 $
b10000000000100100000000000000000 5
b10000000000100100000000000000000 A
b101 V
1R
b11110 S
b11110 Z
1'
#161
b11 ]
#165
0'
#170
b1 V
0R
1'
#175
0'
#180
b100 9
b0 H
b0 \
bx G
bx [
b0 F
b0 W
b10 E
b10 X
b0 D
b1001 I
b11 K
b10 V
b10000000000000100000000000010000 "
b10000000000000100000000000010000 ;
b10000000000000100000000000010000 J
b10000000000000100000000000010000 P
b100100000000100000000000000011 O
1'
#185
0'
#190
b101 <
b10101111110000100000000000000000 !
b10101111110000100000000000000000 ?
b10101111110000100000000000000000 C
b11 V
b11 T
bx %
bx /
bx B
bx N
b0 L
1'
#195
0'
#200
b11111111111111000000000000000 .
b100 V
b11 &
b11 1
b11 @
b11 M
1'
#205
0'
#210
b11111111111111000000000000001 2
bx $
bx 5
bx A
b101 V
b11 Q
b11 Y
1R
b10 S
b10 Z
1'
#211
b100 ]
#215
0'
#220
b11 G
b11 [
b1 V
0R
1'
#225
0'
#230
b101 9
b10000000000100011111111111101000 H
b10000000000100011111111111101000 \
b11110 F
b11110 W
b101011 I
b0 K
b10 V
b10000000000000100000000000010100 "
b10000000000000100000000000010100 ;
b10000000000000100000000000010100 J
b10000000000000100000000000010100 P
b10101111110000100000000000000000 O
1'
#235
0'
#240
b110 <
b100100000000100000000000000010 !
b100100000000100000000000000010 ?
b100100000000100000000000000010 C
b11 V
b0 T
b11 %
b11 /
b11 B
b11 N
b10000000000100011111111111101000 L
1'
#245
0'
#250
b111111111111111010 .
0#
b100 V
1U
b10000000000100011111111111101000 &
b10000000000100011111111111101000 1
b10000000000100011111111111101000 @
b10000000000100011111111111101000 M
1'
#255
0'
#260
1#
04
b111111111111111011 2
b101 V
0U
1'
#261
b101 ]
#265
0'
#270
14
b11 $
b11 5
b11 A
b1 V
1'
#275
0'
#280
b110 9
b0 H
b0 \
b0 F
b0 W
b1001 I
b10 K
b10 V
b10000000000000100000000000011000 "
b10000000000000100000000000011000 ;
b10000000000000100000000000011000 J
b10000000000000100000000000011000 P
b100100000000100000000000000010 O
1'
#285
0'
#290
b111 <
b10101111110000100000000000000100 !
b10101111110000100000000000000100 ?
b10101111110000100000000000000100 C
b11 V
b10 T
b0 L
1'
#295
0'
#300
b11111111111111000000000000000 .
b100 V
b10 &
b10 1
b10 @
b10 M
1'
#305
0'
#310
b11111111111111000000000000001 2
bx $
bx 5
bx A
b101 V
b10 Q
b10 Y
1R
1'
#311
b110 ]
#315
0'
#320
b10 G
b10 [
b1 V
0R
1'
#325
0'
#330
b111 9
b10000000000100011111111111101000 H
b10000000000100011111111111101000 \
b11110 F
b11110 W
b101011 I
b100 K
b10 V
b10000000000000100000000000011100 "
b10000000000000100000000000011100 ;
b10000000000000100000000000011100 J
b10000000000000100000000000011100 P
b10101111110000100000000000000100 O
1'
#335
0'
#340
b1000 <
b10101111110000000000000000001000 !
b10101111110000000000000000001000 ?
b10101111110000000000000000001000 C
b11 V
b100 T
b10 %
b10 /
b10 B
b10 N
b10000000000100011111111111101000 L
1'
#345
0'
#350
b111111111111111011 .
0#
b100 V
1U
b10000000000100011111111111101100 &
b10000000000100011111111111101100 1
b10000000000100011111111111101100 @
b10000000000100011111111111101100 M
1'
#355
0'
#360
1#
04
b111111111111111100 2
b101 V
0U
1'
#361
b111 ]
#365
0'
#370
14
b10 $
b10 5
b10 A
b1 V
1'
#375
0'
#380
b1000 9
b0 G
b0 [
b0 E
b0 X
b1000 K
b10 V
b10000000000000100000000000100000 "
b10000000000000100000000000100000 ;
b10000000000000100000000000100000 J
b10000000000000100000000000100000 P
b10101111110000000000000000001000 O
1'
#385
0'
#390
b1001 <
b10001111110000110000000000000000 !
b10001111110000110000000000000000 ?
b10001111110000110000000000000000 C
b11 V
b1000 T
b0 %
b0 /
b0 B
b0 N
1'
#395
0'
#400
b111111111111111100 .
0#
b100 V
1U
b10000000000100011111111111110000 &
b10000000000100011111111111110000 1
b10000000000100011111111111110000 @
b10000000000100011111111111110000 M
1'
#405
0'
#410
1#
04
b111111111111111101 2
b101 V
b0 S
b0 Z
0U
1'
#411
b1000 ]
#415
0'
#420
14
b0 $
b0 5
b0 A
b1 V
1'
#425
0'
#430
b1001 9
bx G
bx [
b11 E
b11 X
b100011 I
b0 K
b10 V
b10000000000000100000000000100100 "
b10000000000000100000000000100100 ;
b10000000000000100000000000100100 J
b10000000000000100000000000100100 P
b10001111110000110000000000000000 O
1'
#435
0'
#440
b1010 <
b10001111110000100000000000000100 !
b10001111110000100000000000000100 ?
b10001111110000100000000000000100 C
b11 V
b0 T
bx %
bx /
bx B
bx N
1'
#445
0'
#450
b111111111111111010 .
b100 V
b10000000000100011111111111101000 &
b10000000000100011111111111101000 1
b10000000000100011111111111101000 @
b10000000000100011111111111101000 M
1'
#455
0'
#460
b111111111111111011 2
b11 $
b11 5
b11 A
b101 V
b11 S
b11 Z
1'
#461
b1001 ]
#465
0'
#470
b1 V
1R
b11 Q
b11 Y
1'
#475
0'
#480
b1010 9
b10 E
b10 X
b100 K
b10 G
b10 [
b10 V
b10000000000000100000000000101000 "
b10000000000000100000000000101000 ;
b10000000000000100000000000101000 J
b10000000000000100000000000101000 P
b10001111110000100000000000000100 O
0R
1'
#485
0'
#490
b1011 <
b11000100001000000100001 !
b11000100001000000100001 ?
b11000100001000000100001 C
b11 V
b100 T
b10 %
b10 /
b10 B
b10 N
1'
#495
0'
#500
b111111111111111011 .
b100 V
b10000000000100011111111111101100 &
b10000000000100011111111111101100 1
b10000000000100011111111111101100 @
b10000000000100011111111111101100 M
1'
#505
0'
#510
b111111111111111100 2
b10 $
b10 5
b10 A
b101 V
b10 S
b10 Z
1'
#511
b1010 ]
#515
0'
#520
b1 V
1R
b10 Q
b10 Y
1'
#525
0'
#530
b1011 9
b11 H
b11 \
b11 F
b11 W
b10 D
b0 I
b100001 K
b10 V
b10000000000000100000000000101100 "
b10000000000000100000000000101100 ;
b10000000000000100000000000101100 J
b10000000000000100000000000101100 P
b11000100001000000100001 O
0R
1'
#535
0'
#540
b1100 <
b10101111110000100000000000001000 !
b10101111110000100000000000001000 ?
b10101111110000100000000000001000 C
b11 V
b1000000100001 T
b11 L
1'
#545
0'
#550
b11111111111111000000000000001 .
b100 V
b101 &
b101 1
b101 @
b101 M
1'
#555
0'
#560
b11111111111111000000000000010 2
bx $
bx 5
bx A
b101 V
b101 Q
b101 Y
1R
1'
#561
b1011 ]
#565
0'
#570
b101 G
b101 [
b1 V
0R
1'
#575
0'
#580
b1100 9
b10000000000100011111111111101000 H
b10000000000100011111111111101000 \
b11110 F
b11110 W
b0 D
b101011 I
b1000 K
b10 V
b10000000000000100000000000110000 "
b10000000000000100000000000110000 ;
b10000000000000100000000000110000 J
b10000000000000100000000000110000 P
b10101111110000100000000000001000 O
1'
#585
0'
#590
b1101 <
b10001111110000100000000000001000 !
b10001111110000100000000000001000 ?
b10001111110000100000000000001000 C
b11 V
b1000 T
b101 %
b101 /
b101 B
b101 N
b10000000000100011111111111101000 L
1'
#595
0'
#600
b111111111111111100 .
0#
b100 V
1U
b10000000000100011111111111110000 &
b10000000000100011111111111110000 1
b10000000000100011111111111110000 @
b10000000000100011111111111110000 M
1'
#605
0'
#610
1#
04
b111111111111111101 2
b101 V
0U
1'
#611
b1100 ]
#615
0'
#620
14
b101 $
b101 5
b101 A
b1 V
1'
#625
0'
#630
b1101 9
b100011 I
b10 V
b10000000000000100000000000110100 "
b10000000000000100000000000110100 ;
b10000000000000100000000000110100 J
b10000000000000100000000000110100 P
b10001111110000100000000000001000 O
1'
#635
0'
#640
b1110 <
b11110000001110100000100001 !
b11110000001110100000100001 ?
b11110000001110100000100001 C
b11 V
1'
#645
0'
#650
b100 V
1'
#655
0'
#660
b101 V
1'
#661
b1101 ]
#665
0'
#670
b1 V
1R
1'
#675
0'
#680
b1110 9
b0 G
b0 [
b0 E
b0 X
b11101 D
b0 I
b100001 K
b10 V
b10000000000000100000000000111000 "
b10000000000000100000000000111000 ;
b10000000000000100000000000111000 J
b10000000000000100000000000111000 P
b11110000001110100000100001 O
0R
1'
#685
0'
#690
b1111 <
b10001111101111100000000000010100 !
b10001111101111100000000000010100 ?
b10001111101111100000000000010100 C
b11 V
b11111111111111111110100000100001 T
b0 %
b0 /
b0 B
b0 N
1'
#695
0'
#700
b111111111111111010 .
b100 V
b10000000000100011111111111101000 &
b10000000000100011111111111101000 1
b10000000000100011111111111101000 @
b10000000000100011111111111101000 M
1'
#705
0'
#710
b111111111111111011 2
b11 $
b11 5
b11 A
b101 V
b10000000000100011111111111101000 Q
b10000000000100011111111111101000 Y
1R
b11101 S
b11101 Z
1'
#711
b1110 ]
#715
0'
#720
b1 V
0R
1'
#725
0'
#730
b1111 9
b10000000000100011111111111101000 G
b10000000000100011111111111101000 [
b11101 F
b11101 W
b11110 E
b11110 X
b0 D
b100011 I
b10100 K
b10 V
b10000000000000100000000000111100 "
b10000000000000100000000000111100 ;
b10000000000000100000000000111100 J
b10000000000000100000000000111100 P
b10001111101111100000000000010100 O
1'
#735
0'
#740
b10000 <
b100111101111010000000000011000 !
b100111101111010000000000011000 ?
b100111101111010000000000011000 C
b11 V
b10100 T
b10000000000100011111111111101000 %
b10000000000100011111111111101000 /
b10000000000100011111111111101000 B
b10000000000100011111111111101000 N
1'
#745
0'
#750
b111111111111111111 .
b100 V
b10000000000100011111111111111100 &
b10000000000100011111111111111100 1
b10000000000100011111111111111100 @
b10000000000100011111111111111100 M
1'
#755
0'
#760
b1000000000000000000 2
bx $
bx 5
bx A
b101 V
b11110 S
b11110 Z
1'
#761
b1111 ]
#765
0'
#770
b1 V
1R
bx Q
bx Y
1'
#775
0'
#780
b10000 9
b11101 E
b11101 X
b1001 I
b11000 K
b10000000000100011111111111101000 G
b10000000000100011111111111101000 [
b10 V
b10000000000000100000000001000000 "
b10000000000000100000000001000000 ;
b10000000000000100000000001000000 J
b10000000000000100000000001000000 P
b100111101111010000000000011000 O
0R
1'
#785
0'
#790
b10001 <
b11111000000000000000001000 !
b11111000000000000000001000 ?
b11111000000000000000001000 C
b11 V
b11000 T
1'
#795
0'
#800
b1000000000000000000 .
b100 V
b10000000000100100000000000000000 &
b10000000000100100000000000000000 1
b10000000000100100000000000000000 @
b10000000000100100000000000000000 M
1'
#805
0'
#810
b1000000000000000001 2
b101 V
b10000000000100100000000000000000 Q
b10000000000100100000000000000000 Y
1R
b11101 S
b11101 Z
1'
#811
b10000 ]
#815
0'
#820
b10000000000100100000000000000000 H
b10000000000100100000000000000000 \
b10000000000100100000000000000000 G
b10000000000100100000000000000000 [
b1 V
0R
1'
#825
0'
#830
b10001 9
b0 H
b0 \
b0 G
b0 [
b11111 F
b11111 W
b0 E
b0 X
b0 I
b1000 K
b10 V
b10000000000000100000000001000100 "
b10000000000000100000000001000100 ;
b10000000000000100000000001000100 J
b10000000000000100000000001000100 P
b11111000000000000000001000 O
1'
#835
0'
#840
b10010 <
b0 !
b0 ?
b0 C
b11 V
b1000 T
b0 %
b0 /
b0 B
b0 N
b0 L
1'
#845
0'
#850
b11111111111111000000000000000 .
b100 V
b0 &
b0 1
b0 @
b0 M
1'
#855
0'
#860
b11111111111111000000000000001 2
b101 V
b0 S
b0 Z
1'
#861
b10001 ]
#865
0'
#870
b1 V
1'
